cobras/__init__.py
cobras/bavarde/__init__.py
cobras/bavarde/bot/__init__.py
cobras/bavarde/bot/bot.py
cobras/bavarde/client/__init__.py
cobras/bavarde/client/client.py
cobras/bavarde/client/encryption.py
cobras/bavarde/runner/__init__.py
cobras/bavarde/runner/bot.py
cobras/bavarde/runner/client.py
cobras/bavarde/runner/daemon.py
cobras/client/__init__.py
cobras/client/client.py
cobras/client/connection.py
cobras/client/credentials.py
cobras/client/health_check.py
cobras/client/monitor.py
cobras/client/publish.py
cobras/common/__init__.py
cobras/common/algorithm.py
cobras/common/apps_config.py
cobras/common/atexit_profiler.py
cobras/common/auth_hash.py
cobras/common/banner.py
cobras/common/channel_builder.py
cobras/common/cobra_types.py
cobras/common/memoize.py
cobras/common/memory_debugger.py
cobras/common/memory_usage.py
cobras/common/task_cleanup.py
cobras/common/throttle.py
cobras/common/version.py
cobras/data/publish.jsonl
cobras/runner/__init__.py
cobras/runner/admin.py
cobras/runner/health.py
cobras/runner/init.py
cobras/runner/monitor.py
cobras/runner/publish.py
cobras/runner/read.py
cobras/runner/redis_cluster.py
cobras/runner/run.py
cobras/runner/secret.py
cobras/runner/subscribe.py
cobras/runner/write.py
cobras/server/__init__.py
cobras/server/app.py
cobras/server/connection_state.py
cobras/server/pipelined_publisher.py
cobras/server/pipelined_publishers.py
cobras/server/protocol.py
cobras/server/pulsar.py
cobras/server/rcc_client.py
cobras/server/redis_clients.py
cobras/server/stats.py
cobras/server/stream_sql.py
cobras/server/handlers/__init__.py
cobras/server/handlers/admin.py
cobras/server/handlers/auth.py
cobras/server/handlers/kv_store.py
cobras/server/handlers/pubsub.py
cobras/server/justredis/__init__.py
cobras/server/justredis/justredis.py
cobras-2.9.137.dist-info/LICENSE.txt
cobras-2.9.137.dist-info/METADATA
cobras-2.9.137.dist-info/WHEEL
cobras-2.9.137.dist-info/entry_points.txt
cobras-2.9.137.dist-info/top_level.txt
cobras-2.9.137.dist-info/RECORD
