Metadata-Version: 2.1
Name: cobras
Version: 2.9.137
Summary: A realtime messaging server using WebSockets and Redis.
Home-page: https://github.com/machinezone/cobra
Author: Benjamin Sergeant
Author-email: bsergean@gmail.com
License: BSD 3
Platform: UNKNOWN
Classifier: Development Status :: 5 - Production/Stable
Classifier: Environment :: Web Environment
Classifier: Intended Audience :: Developers
Classifier: License :: OSI Approved :: BSD License
Classifier: Operating System :: OS Independent
Classifier: Programming Language :: Python
Classifier: Programming Language :: Python :: 3
Classifier: Programming Language :: Python :: 3.6
Classifier: Programming Language :: Python :: 3.7
Classifier: Programming Language :: Python :: 3.8
Classifier: Programming Language :: Python :: 3.9
Requires-Dist: aioredis (==1.3.1)
Requires-Dist: aredis (==1.1.8)
Requires-Dist: click (>=7.0)
Requires-Dist: coloredlogs (==10.0)
Requires-Dist: daemonize (==2.5.0)
Requires-Dist: hiredis (==1.0.1)
Requires-Dist: humanfriendly (==4.18)
Requires-Dist: klaxon (==1.1.0)
Requires-Dist: psutil (==5.6.6)
Requires-Dist: pyaes (==1.6.1)
Requires-Dist: PyYAML (==5.2)
Requires-Dist: rcc (==0.9.154)
Requires-Dist: sentry-sdk (>=0.13.5)
Requires-Dist: tabulate (==0.8.5)
Requires-Dist: uhashring (==1.1)
Requires-Dist: websockets (==8.1)
Provides-Extra: dev
Requires-Dist: wheel ; extra == 'dev'
Requires-Dist: isort ; extra == 'dev'
Requires-Dist: mypy ; extra == 'dev'
Requires-Dist: twine ; extra == 'dev'
Requires-Dist: black ; extra == 'dev'
Requires-Dist: pre-commit ; extra == 'dev'
